ethernity_cloud_sdk_py/__init__.py
ethernity_cloud_sdk_py/cli.py
ethernity_cloud_sdk_py/commands/__init__.py
ethernity_cloud_sdk_py/commands/build.py
ethernity_cloud_sdk_py/commands/config.py
ethernity_cloud_sdk_py/commands/enums.py
ethernity_cloud_sdk_py/commands/init.py
ethernity_cloud_sdk_py/commands/private_key.py
ethernity_cloud_sdk_py/commands/publish.py
ethernity_cloud_sdk_py/commands/spinner.py
ethernity_cloud_sdk_py/commands/__pycache__/__init__.cpython-311.pyc
ethernity_cloud_sdk_py/commands/__pycache__/build.cpython-311.pyc
ethernity_cloud_sdk_py/commands/__pycache__/config.cpython-311.pyc
ethernity_cloud_sdk_py/commands/__pycache__/enums.cpython-311.pyc
ethernity_cloud_sdk_py/commands/__pycache__/init.cpython-311.pyc
ethernity_cloud_sdk_py/commands/__pycache__/private_key.cpython-311.pyc
ethernity_cloud_sdk_py/commands/__pycache__/publish.cpython-311.pyc
ethernity_cloud_sdk_py/commands/__pycache__/spinner.cpython-311.pyc
ethernity_cloud_sdk_py/commands/pynithy/__init__.py
ethernity_cloud_sdk_py/commands/pynithy/build.py
ethernity_cloud_sdk_py/commands/pynithy/ipfs_client.py
ethernity_cloud_sdk_py/commands/pynithy/publish.py
ethernity_cloud_sdk_py/commands/pynithy/__pycache__/__init__.cpython-311.pyc
ethernity_cloud_sdk_py/commands/pynithy/__pycache__/build.cpython-311.pyc
ethernity_cloud_sdk_py/commands/pynithy/__pycache__/ipfs_client.cpython-311.pyc
ethernity_cloud_sdk_py/commands/pynithy/__pycache__/publish.cpython-311.pyc
ethernity_cloud_sdk_py/commands/pynithy/build/securelock/Dockerfile.base
ethernity_cloud_sdk_py/commands/pynithy/build/securelock/Dockerfile.base.tpl
ethernity_cloud_sdk_py/commands/pynithy/build/securelock/Dockerfile.tpl
ethernity_cloud_sdk_py/commands/pynithy/build/securelock/scripts/binary-fs-build.sh
ethernity_cloud_sdk_py/commands/pynithy/build/securelock/src/etny_crypto.py
ethernity_cloud_sdk_py/commands/pynithy/build/securelock/src/etny_exec.py
ethernity_cloud_sdk_py/commands/pynithy/build/securelock/src/etny_exec_flask.py
ethernity_cloud_sdk_py-0.3.3.dist-info/licenses/LICENSE
ethernity_cloud_sdk_py-0.3.3.dist-info/METADATA
ethernity_cloud_sdk_py-0.3.3.dist-info/WHEEL
ethernity_cloud_sdk_py-0.3.3.dist-info/entry_points.txt
ethernity_cloud_sdk_py-0.3.3.dist-info/top_level.txt
ethernity_cloud_sdk_py-0.3.3.dist-info/RECORD
