Metadata-Version: 2.4
Name: ethernity-cloud-sdk-py
Version: 0.3.3
Summary: Ethernity Cloud SDK Python
Home-page: https://github.com/ethernity-cloud/ethernity-cloud-sdk-py
Author: Ethernity Cloud Team
Author-email: contact@ethernity.cloud
License-File: LICENSE
Requires-Dist: requests
Requires-Dist: python-dotenv
Requires-Dist: tqdm
Requires-Dist: pyopenssl
Requires-Dist: requests_toolbelt
Requires-Dist: cryptography
Requires-Dist: typing-extensions
Requires-Dist: ethernity-cloud-runner-py
Requires-Dist: pyyaml
Dynamic: author
Dynamic: author-email
Dynamic: description
Dynamic: description-content-type
Dynamic: home-page
Dynamic: license-file
Dynamic: requires-dist
Dynamic: summary
